_fedmod/__init__.py
_fedmod/__main__.py
_fedmod/_depchase.py
_fedmod/_repodata.py
_fedmod/cli.py
_fedmod/module_generator.py
fedmod-0.0.5.dist-info/DESCRIPTION.rst
fedmod-0.0.5.dist-info/METADATA
fedmod-0.0.5.dist-info/RECORD
fedmod-0.0.5.dist-info/WHEEL
fedmod-0.0.5.dist-info/entry_points.txt
fedmod-0.0.5.dist-info/metadata.json
fedmod-0.0.5.dist-info/top_level.txt
