Metadata-Version: 2.0
Name: fedmod
Version: 0.0.5
Summary: Utilities for generating & maintaining modulemd files
Home-page: https://pagure.io/modularity/fedmod
Author: Nick Coghlan
Author-email: ncoghlan@redhat.com
License: MIT
Keywords: modularization modularity module modulemd fedora
Platform: UNKNOWN
Requires-Dist: modulemd
Requires-Dist: click
Requires-Dist: requests
Requires-Dist: requests-toolbelt
Requires-Dist: lxml
Requires-Dist: attrs
